var RCMPinfrastructure = {
"type": "FeatureCollection",
"name": "RCMP-infrastructure",
"crs": { "type": "name", "properties": { "name": "urn:ogc:def:crs:OGC:1.3:CRS84" } },
"features": [
{ "type": "Feature", "properties": { "id": 1, "TITLE": "RCMP Checkpoint", "DATE": null, "DESC": "Start of Exclusion Zone. Constant armed RCMP presence to control access to interior territory.", "SLUG": "checkpoint", "auxiliary_storage_labeling_positionx": -127.03415636099983, "auxiliary_storage_labeling_positiony": 54.479685845022551 }, "geometry": { "type": "Point", "coordinates": [ -126.883284334619219, 54.204900860995743 ] } }
]
}
